gitsnipe/__init__.py
gitsnipe/cli.py
gitsnipe/core.py
gitsnipe-1.0.1.dist-info/METADATA
gitsnipe-1.0.1.dist-info/WHEEL
gitsnipe-1.0.1.dist-info/entry_points.txt
gitsnipe-1.0.1.dist-info/top_level.txt
gitsnipe-1.0.1.dist-info/RECORD
