Metadata-Version: 2.4
Name: gitsnipe
Version: 1.0.1
Summary: A powerful tool for scanning and cloning Git repositories with exposed .git/config files
Home-page: https://github.com/ishanoshada/GitSnipe
Author: Ishan Oshada
Author-email: example@example.com
License: MIT
Project-URL: Bug Reports, https://github.com/ishanoshada/GitSnipe/issues
Project-URL: Source, https://github.com/ishanoshada/GitSnipe
Project-URL: Documentation, https://github.com/ishanoshada/GitSnipe#readme
Keywords: git security scanning repository clone config credentials automation tool
Classifier: Programming Language :: Python :: 3
Classifier: Programming Language :: Python :: 3.7
Classifier: Programming Language :: Python :: 3.8
Classifier: Programming Language :: Python :: 3.9
Classifier: Programming Language :: Python :: 3.10
Classifier: License :: OSI Approved :: MIT License
Classifier: Operating System :: OS Independent
Classifier: Development Status :: 5 - Production/Stable
Classifier: Intended Audience :: Developers
Classifier: Topic :: Security
Classifier: Topic :: Software Development :: Version Control :: Git
Requires-Python: >=3.7
Requires-Dist: requests>=2.28.0
Requires-Dist: configparser>=5.3.0
Requires-Dist: gitpython>=3.1.30
Requires-Dist: rich>=13.0.0
Requires-Dist: typer>=0.9.0
Requires-Dist: git-dumper>=1.0.0
Dynamic: author
Dynamic: author-email
Dynamic: classifier
Dynamic: description
Dynamic: description-content-type
Dynamic: home-page
Dynamic: keywords
Dynamic: license
Dynamic: project-url
Dynamic: requires-dist
Dynamic: requires-python
Dynamic: summary
